application_example/__init__.py
application_example/example.py
keepcoodingtest_pedro-0.0.2.dist-info/METADATA
keepcoodingtest_pedro-0.0.2.dist-info/WHEEL
keepcoodingtest_pedro-0.0.2.dist-info/top_level.txt
keepcoodingtest_pedro-0.0.2.dist-info/RECORD
