Metadata-Version: 2.1
Name: keepcoodingtest-pedro
Version: 0.0.2
Summary: example
Author: keepcooder
Author-email: kcpypitest@gmail.com
License: UNKNOWN
Platform: UNKNOWN
Requires-Python: >=3.6
Requires-Dist: build
Requires-Dist: twine
Requires-Dist: coloredlogs
